telenotif/__init__.py
telenotif/exceptions.py
telenotif/notif.py
telenotif-0.1.3.dist-info/METADATA
telenotif-0.1.3.dist-info/WHEEL
telenotif-0.1.3.dist-info/top_level.txt
telenotif-0.1.3.dist-info/RECORD
