Metadata-Version: 2.1
Name: telenotif
Version: 0.1.3
Summary: A simple notification library using Telegram bots
Home-page: https://github.com/Sinamirshahi/telenotif
Author: Sina
Author-email: Sina <sina7th@gmail.com>
License: MIT
Keywords: telegram,notification,bot
Classifier: Programming Language :: Python :: 3
Classifier: License :: OSI Approved :: MIT License
Classifier: Operating System :: OS Independent
Requires-Python: >=3.7
Requires-Dist: python-telegram-bot>=20.0
Requires-Dist: nest-asyncio>=1.5.6
